{
  "_class": "symbolInstance",
  "do_objectID": "8C3C219F-273E-4781-858F-59160F5005A5",
  "exportOptions": {
    "_class": "exportOptions",
    "exportFormats": [
    ],
    "includedLayerIds": [
    ],
    "layerOptions": 0,
    "shouldTrim": false
  },
  "frame": {
    "_class": "rect",
    "constrainProportions": false,
    "height": 67,
    "width": 363,
    "x": 0,
    "y": 0
  },
  "horizontalSpacing": 0,
  "isFlippedHorizontal": false,
  "isFlippedVertical": false,
  "isLocked": false,
  "isVisible": true,
  "layerListExpandedType": 0,
  "masterInfluenceEdgeMaxXPadding": 0,
  "masterInfluenceEdgeMaxYPadding": 1,
  "masterInfluenceEdgeMinXPadding": 0,
  "masterInfluenceEdgeMinYPadding": 0,
  "name": "test",
  "nameIsFixed": false,
  "overrides": {
    "1F25939A-9E74-46C9-BBBB-3ED5E2C72720": {
      "_class": "MSJSONFileReference",
      "_ref": "images/79b336064d8398d5d550cd5277b2ae0ad933ec64",
      "_ref_class": "MSImageData"
    }
  },
  "resizingConstraint": 63,
  "resizingType": 0,
  "rotation": 0,
  "shouldBreakMaskChain": false,
  "style": {
    "_class": "style",
    "endDecorationType": 0,
    "miterLimit": 10,
    "startDecorationType": 0
  },
  "symbolID": "4F49B0F3-25D7-41B7-95F0-47B9F26B68E7",
  "userInfo": {
    "com.animaapp.stc-sketch-plugin": {
      "kModelPropertiesKey": {
      }
    }
  },
  "verticalSpacing": 0
}